flashtext2-1.1.0.dist-info/METADATA
flashtext2-1.1.0.dist-info/WHEEL
flashtext2-1.1.0.dist-info/license_files/LICENSE
flashtext2/__init__.py
flashtext2/__init__.pyi
flashtext2/py.typed
flashtext2/flashtext2.pyd
flashtext2-1.1.0.dist-info/RECORD
