Metadata-Version: 2.3
Name: flashtext2
Version: 1.1.0
Classifier: Development Status :: 5 - Production/Stable
Classifier: License :: OSI Approved :: MIT License
Classifier: Programming Language :: Rust
Classifier: Programming Language :: Python :: 3 :: Only
Classifier: Programming Language :: Python :: 3
Classifier: Programming Language :: Python :: 3.8
Classifier: Programming Language :: Python :: 3.9
Classifier: Programming Language :: Python :: 3.10
Classifier: Programming Language :: Python :: 3.11
Classifier: Programming Language :: Python :: 3.12
Classifier: Programming Language :: Python :: Implementation :: CPython
Classifier: Programming Language :: Python :: Implementation :: PyPy
Requires-Dist: coverage >=7.2.1 ; extra == 'test'
Requires-Dist: pytest >=7.2.1 ; extra == 'test'
Requires-Dist: flashtext >=2.7 ; extra == 'benchmark'
Requires-Dist: pandas >=2.0.3 ; extra == 'benchmark'
Requires-Dist: matplotlib >=3.7.2 ; extra == 'benchmark'
Provides-Extra: test
Provides-Extra: benchmark
License-File: LICENSE
Summary: A package for extracting keywords from large text very quickly (much faster than regex and the original flashtext package
Keywords: nlp,string,regex,text-processing,extracting-keywords,keyword-extraction,flashtext,flashtext2,rust
Home-Page: https://github.com/shner-elmo/flashtext2-rs
Author: Shneor E.
Author-email: "Shneor E." <770elmo@gmail.com>
License: MIT
Requires-Python: >=3.8
Project-URL: homepage, https://github.com/shner-elmo/flashtext2
Project-URL: source, https://github.com/shner-elmo/flashtext2
Project-URL: repository, https://github.com/shner-elmo/flashtext2
Project-URL: documentation, https://github.com/shner-elmo/flashtext2/blob/master/README.md
Project-URL: Bug Reports, https://github.com/shner-elmo/flashtext2/issues
